astlab/__init__.py
astlab/_typing.py
astlab/abc.py
astlab/builder.py
astlab/cache.py
astlab/context.py
astlab/py.typed
astlab/reader.py
astlab/resolver.py
astlab/traverse.py
astlab/types/__init__.py
astlab/types/annotator.py
astlab/types/inspector.py
astlab/types/loader.py
astlab/types/model.py
astlab/types/predef.py
astlab/version.py
astlab/writer.py
astlab-0.5.2.dist-info/METADATA
astlab-0.5.2.dist-info/WHEEL
astlab-0.5.2.dist-info/licenses/LICENSE
astlab-0.5.2.dist-info/RECORD
