Metadata-Version: 2.4
Name: astlab
Version: 0.5.2
Summary: provides an intuitive API for building and manipulating Abstract Syntax Trees (ASTs) to generate Python code.
License: MIT
License-File: LICENSE
Keywords: python,codegen,ast
Author: zerlok
Author-email: danil.troshnev@gmail.com
Requires-Python: >=3.9,<4.0
Classifier: Development Status :: 3 - Alpha
Classifier: Intended Audience :: Developers
Classifier: License :: OSI Approved :: MIT License
Classifier: Operating System :: OS Independent
Classifier: Programming Language :: Python :: 3
Classifier: Programming Language :: Python :: 3.9
Classifier: Programming Language :: Python :: 3.10
Classifier: Programming Language :: Python :: 3.11
Classifier: Programming Language :: Python :: 3.12
Classifier: Programming Language :: Python :: 3.13
Classifier: Programming Language :: Python :: 3.14
Classifier: Topic :: Software Development :: Code Generators
Classifier: Typing :: Typed
Project-URL: Homepage, https://github.com/zerlok/astlab
Project-URL: Issues, https://github.com/zerlok/astlab/issues
